toy_pypkg/__init__.py
toy_pypkg/toy_pypkg.py
toy_pypkg-0.1.0.dist-info/LICENSE
toy_pypkg-0.1.0.dist-info/WHEEL
toy_pypkg-0.1.0.dist-info/METADATA
toy_pypkg-0.1.0.dist-info/RECORD
