Metadata-Version: 2.1
Name: toy-pypkg
Version: 0.1.0
Summary: Toy python packag (test)
License: MIT
Author: mmyz
Author-email: yzmarco.ma@gmail.com
Requires-Python: >=3.8,<4.0
Classifier: License :: OSI Approved :: MIT License
Classifier: Programming Language :: Python :: 3
Classifier: Programming Language :: Python :: 3.8
Classifier: Programming Language :: Python :: 3.9
Requires-Dist: pandas (>=1.2.2,<2.0.0)
Requires-Dist: pytest (>=6.2.2,<7.0.0)
